{
  "Name": "TopDown",
  "ShaderNames": [
    "VertexTopDown",
    "FragmentTopDown"
  ],
  "Inputs": [
    {
      "Id": 0,
      "Offset": 0,
      "Layout": 103
    },
    {
      "Id": 1,
      "Offset": 8,
      "Layout": 103
    }
  ],
  "Descriptors": [
    {
      "Binding": 0,
      "Type": 6,
      "flag": 1
    },
    {
      "Binding": 1,
      "Type": 0,
      "flag": 16
    },
    {
      "Binding": 2,
      "Type": 2,
      "flag": 16
    },
    {
      "Binding": 3,
      "Type": 6,
      "flag": 16
    }
  ]
}